{
	"type" : "FeatureCollection",
	"name" : "geojson_biodiv",
	"features" : [
		{
			"type" : "Feature",
			"geometry" : {
				"type" : "Point",
				"coordinates" : [ -1.577680707, 48.2189148753 ]
			},
			"properties" : {
				"année" : "2021-2022",
				"armature" : "Pôle de proximité à conforter",
				"cout_global" : 400000,
				"montant_attrib" : 90000,
				"intitulé" : "Végétalisation du cimetière ",
				"nature" : "3- Biodiversité",
				"taux" : 30,
				"Maitrise d'ouvrage" : "Saint-Sulpice la Forêt"
			}
		},
		{
			"type" : "Feature",
			"geometry" : {
				"type" : "Point",
				"coordinates" : [ -1.4829783731, 48.1106665983 ]
			},
			"properties" : {
				"année" : "2021-2022",
				"armature" : "Pôle de proximité ",
				"cout_global" : 142000,
				"montant_attrib" : 42600,
				"intitulé" : "Parcours sportif intégrant des enjeux de biodiversité",
				"justificatif" : "PBIL",
				"nature" : "3- Biodiversité",
				"taux" : 30,
				"Maitrise d'ouvrage" : "Brécé"
			}
		},
		{
			"type" : "Feature",
			"geometry" : {
				"type" : "Point",
				"coordinates" : [ -1.7460353293, 48.0244546199 ]
			},
			"properties" : {
				"année" : "2021-2022",
				"armature" : "Pôle d'appui cœur de métropole et pôle structurant ",
				"cout_global" : 100000,
				"montant_attrib" : 30000,
				"intitulé" : "Végétalisation du cimetière pour entretien éco-responsable",
				"nature" : "3- Biodiversité",
				"taux" : 30,
				"Maitrise d'ouvrage" : "Bruz"
			}
		},
		{
			"type" : "Feature",
			"geometry" : {
				"type" : "Point",
				"coordinates" : [ -1.8468391669, 48.0732055894 ]
			},
			"properties" : {
				"année" : "2021-2022",
				"armature" : "Pôle d'appui cœur de métropole et pôle structurant ",
				"cout_global" : 411991,
				"montant_attrib" : 90000,
				"intitulé" : "Sentier d'interprétation sur la reconquête de l'eau et des milieux aquatiques",
				"justificatif" : "Performance énergétique",
				"nature" : "3- Biodiversité",
				"taux" : 30,
				"Maitrise d'ouvrage" : "Mordelles"
			}
		},
		{
			"type" : "Feature",
			"geometry" : {
				"type" : "Point",
				"coordinates" : [ -1.8314019475, 48.1917295205 ]
			},
			"properties" : {
				"année" : "2021-2022",
				"armature" : "Pôle de proximité à conforter",
				"cout_global" : 30870,
				"montant_attrib" : 9261,
				"intitulé" : "Création d'une tiny-forest",
				"nature" : "3- Biodiversité",
				"taux" : 30,
				"Maitrise d'ouvrage" : "Parthenay-de-Bretagne"
			}
		},
		{
			"type" : "Feature",
			"geometry" : {
				"type" : "Point",
				"coordinates" : [ -1.8924325705, 48.2155192362 ]
			},
			"properties" : {
				"année" : "2021-2022",
				"armature" : "Pôle de proximité ",
				"cout_global" : 599654,
				"montant_attrib" : 90000,
				"intitulé" : "Requalification paysagère du chemin creux de la Houltais",
				"nature" : "3- Biodiversité",
				"taux" : 30,
				"Maitrise d'ouvrage" : "Romillé"
			}
		},
		{
			"type" : "Feature",
			"geometry" : {
				"type" : "Point",
				"coordinates" : [ -1.6016689616, 48.0446618576 ]
			},
			"properties" : {
				"année" : "2021-2022",
				"armature" : "Pôle d'appui cœur de métropole et pôle structurant ",
				"cout_global" : 93000,
				"montant_attrib" : 27900,
				"intitulé" : "Aménagement du Clos d'Orrière",
				"nature" : "3- Biodiversité",
				"taux" : 30,
				"Maitrise d'ouvrage" : "Vern-sur-Seiche"
			}
		}
	]
}